{"cameraMode":{"drawMode":0,"name":"Shaded","section":"Shading Mode"},"sceneLighting":true,"audioPlay":false,"sceneViewState":{"showFog":true,"showMaterialUpdate":false,"showSkybox":true,"showFlares":true,"showImageEffects":true,"showParticleSystems":true,"showVisualEffectGraphs":true,"m_FxEnabled":true},"in2DMode":false,"pivot":{"x":5.155220031738281,"y":11.445816040039063,"z":-3.913482666015625},"rotation":{"x":0.226972296833992,"y":0.17449715733528138,"z":-0.04137372225522995,"w":0.9572485089302063},"size":136.30960083007813,"orthographic":false}